rpgmaker_mv_decoder/__init__.py
rpgmaker_mv_decoder/callbacks.py
rpgmaker_mv_decoder/cli_help.py
rpgmaker_mv_decoder/clickdisplay.py
rpgmaker_mv_decoder/constants.py
rpgmaker_mv_decoder/exceptions.py
rpgmaker_mv_decoder/messagetypes.py
rpgmaker_mv_decoder/project.py
rpgmaker_mv_decoder/projectdecoder.py
rpgmaker_mv_decoder/projectencoder.py
rpgmaker_mv_decoder/projectkeyfinder.py
rpgmaker_mv_decoder/projectpaths.py
rpgmaker_mv_decoder/promptresponse.py
rpgmaker_mv_decoder/utils.py
rpgmaker_mv_decoder-1.4.0.dist-info/AUTHORS.rst
rpgmaker_mv_decoder-1.4.0.dist-info/LICENSE
rpgmaker_mv_decoder-1.4.0.dist-info/METADATA
rpgmaker_mv_decoder-1.4.0.dist-info/WHEEL
rpgmaker_mv_decoder-1.4.0.dist-info/entry_points.txt
rpgmaker_mv_decoder-1.4.0.dist-info/top_level.txt
rpgmaker_mv_decoder-1.4.0.dist-info/RECORD
