Metadata-Version: 2.1
Name: rpgmaker-mv-decoder
Version: 1.4.0
Summary: Quickly decode or encode assets for RPG Maker MV, even if you don't have the key
Home-page: https://github.com/kins-dev/rpgmaker_mv_decoder
Author: Scott Atkins
Author-email: scott@kins.dev
License: MIT license
Keywords: rpgmaker_mv_decoder
Platform: UNKNOWN
Classifier: Development Status :: 5 - Production/Stable
Classifier: Intended Audience :: End Users/Desktop
Classifier: License :: OSI Approved :: MIT License
Classifier: Natural Language :: English
Classifier: Programming Language :: Python :: 3
Classifier: Programming Language :: Python :: 3.6
Classifier: Programming Language :: Python :: 3.7
Classifier: Programming Language :: Python :: 3.8
Classifier: Programming Language :: Python :: 3.9
Classifier: Programming Language :: Python :: 3.10
Requires-Python: >=3.6
License-File: LICENSE
License-File: AUTHORS.rst
Requires-Dist: Click (>=7.0)
Requires-Dist: python-magic (>=0.4.16)
Requires-Dist: pygubu (>=0.20)
